flake8_breakpoint/__init__.py
flake8_breakpoint/errors.py
flake8_breakpoint/plugin.py
flake8_breakpoint/visitors.py
flake8_breakpoint-1.1.0.dist-info/entry_points.txt
flake8_breakpoint-1.1.0.dist-info/LICENSE
flake8_breakpoint-1.1.0.dist-info/WHEEL
flake8_breakpoint-1.1.0.dist-info/METADATA
flake8_breakpoint-1.1.0.dist-info/RECORD
