Metadata-Version: 2.1
Name: flake8-breakpoint
Version: 1.1.0
Summary: Flake8 plugin that check forgotten breakpoints
Home-page: https://pypi.org/project/flake8-breakpoint
Author: Evgeniy Afonasev
Author-email: ea.afonasev@gmail.com
Keywords: flake8,linter,breakpoint,debug
Requires-Python: >=3.6,<4.0
Classifier: License :: OSI Approved :: MIT License
Classifier: Programming Language :: Python :: 3
Classifier: Programming Language :: Python :: 3.6
Classifier: Programming Language :: Python :: 3.7
Requires-Dist: flake8-plugin-utils (>=1.0,<2.0)
Project-URL: Repository, https://github.com/afonasev/flake8-breakpoint
